calculator.py
mcp_calculator-0.1.0.dist-info/METADATA
mcp_calculator-0.1.0.dist-info/WHEEL
mcp_calculator-0.1.0.dist-info/top_level.txt
mcp_calculator-0.1.0.dist-info/RECORD
