Metadata-Version: 2.4
Name: mcp-calculator
Version: 0.1.0
Summary: Add your description here
Requires-Python: >=3.13
Requires-Dist: mcp[cli]>=1.7.1
